umitkavala_zeroc-1.0.2.dist-info/licenses/LICENSE
zeroc/__init__.py
zeroc/dictionary_loader.py
zeroc/py.typed
zeroc/wire_format.py
umitkavala_zeroc-1.0.2.dist-info/METADATA
umitkavala_zeroc-1.0.2.dist-info/WHEEL
umitkavala_zeroc-1.0.2.dist-info/top_level.txt
umitkavala_zeroc-1.0.2.dist-info/RECORD
