Metadata-Version: 2.4
Name: umitkavala-zeroc
Version: 1.0.2
Summary: Zeroc: High-Performance API Compression Protocol
Home-page: https://github.com/umitkavala/zeroc
Author: Umit Kavala
License: MIT
Project-URL: Homepage, https://github.com/umitkavala/zeroc
Project-URL: Documentation, https://github.com/umitkavala/zeroc/tree/main/spec
Project-URL: Repository, https://github.com/umitkavala/zeroc
Project-URL: Issues, https://github.com/umitkavala/zeroc/issues
Project-URL: Changelog, https://github.com/umitkavala/zeroc/releases
Keywords: compression,protobuf,zstd,zstandard,api,performance,bandwidth,serialization
Classifier: Development Status :: 4 - Beta
Classifier: Intended Audience :: Developers
Classifier: License :: OSI Approved :: MIT License
Classifier: Operating System :: OS Independent
Classifier: Programming Language :: Python :: 3
Classifier: Programming Language :: Python :: 3.8
Classifier: Programming Language :: Python :: 3.9
Classifier: Programming Language :: Python :: 3.10
Classifier: Programming Language :: Python :: 3.11
Classifier: Programming Language :: Python :: 3.12
Classifier: Topic :: Software Development :: Libraries :: Python Modules
Classifier: Topic :: System :: Archiving :: Compression
Classifier: Topic :: Internet :: WWW/HTTP
Classifier: Typing :: Typed
Requires-Python: >=3.8
License-File: LICENSE
Requires-Dist: zstandard>=0.21.0
Requires-Dist: crc32c>=2.3
Provides-Extra: dev
Requires-Dist: pytest>=7.0.0; extra == "dev"
Requires-Dist: pytest-cov>=4.0.0; extra == "dev"
Requires-Dist: pytest-benchmark>=4.0.0; extra == "dev"
Requires-Dist: pyright>=1.1.0; extra == "dev"
Requires-Dist: ruff>=0.1.0; extra == "dev"
Requires-Dist: types-protobuf>=4.0.0; extra == "dev"
Provides-Extra: docs
Requires-Dist: mkdocs>=1.5.0; extra == "docs"
Requires-Dist: mkdocs-material>=9.0.0; extra == "docs"
Requires-Dist: mkdocstrings[python]>=0.24.0; extra == "docs"
Dynamic: home-page
Dynamic: license-file
Dynamic: requires-python
